avalanche/__init__.py
avalanche/_annotations.py
avalanche/core.py
avalanche/benchmarks/__init__.py
avalanche/benchmarks/classic/__init__.py
avalanche/benchmarks/classic/ccifar10.py
avalanche/benchmarks/classic/ccifar100.py
avalanche/benchmarks/classic/ccub200.py
avalanche/benchmarks/classic/cfashion_mnist.py
avalanche/benchmarks/classic/cimagenet.py
avalanche/benchmarks/classic/cinaturalist.py
avalanche/benchmarks/classic/classic_benchmarks_utils.py
avalanche/benchmarks/classic/clear.py
avalanche/benchmarks/classic/cmnist.py
avalanche/benchmarks/classic/comniglot.py
avalanche/benchmarks/classic/core50.py
avalanche/benchmarks/classic/ctiny_imagenet.py
avalanche/benchmarks/classic/ctrl.py
avalanche/benchmarks/classic/endless_cl_sim.py
avalanche/benchmarks/classic/ex_model.py
avalanche/benchmarks/classic/openloris.py
avalanche/benchmarks/classic/stream51.py
avalanche/benchmarks/datasets/__init__.py
avalanche/benchmarks/datasets/dataset_utils.py
avalanche/benchmarks/datasets/downloadable_dataset.py
avalanche/benchmarks/datasets/imagenet_data.py
avalanche/benchmarks/datasets/omniglot.py
avalanche/benchmarks/datasets/torchaudio_wrapper.py
avalanche/benchmarks/datasets/torchvision_wrapper.py
avalanche/benchmarks/datasets/clear/__init__.py
avalanche/benchmarks/datasets/clear/clear.py
avalanche/benchmarks/datasets/clear/clear_data.py
avalanche/benchmarks/datasets/core50/__init__.py
avalanche/benchmarks/datasets/core50/core50.py
avalanche/benchmarks/datasets/core50/core50_data.py
avalanche/benchmarks/datasets/cub200/__init__.py
avalanche/benchmarks/datasets/cub200/cub200.py
avalanche/benchmarks/datasets/endless_cl_sim/__init__.py
avalanche/benchmarks/datasets/endless_cl_sim/endless_cl_sim.py
avalanche/benchmarks/datasets/endless_cl_sim/endless_cl_sim_data.py
avalanche/benchmarks/datasets/external_datasets/__init__.py
avalanche/benchmarks/datasets/external_datasets/cifar.py
avalanche/benchmarks/datasets/external_datasets/fmnist.py
avalanche_lib-0.6.0.dist-info/LICENSE
avalanche_lib-0.6.0.dist-info/METADATA
avalanche_lib-0.6.0.dist-info/WHEEL
avalanche_lib-0.6.0.dist-info/top_level.txt
avalanche_lib-0.6.0.dist-info/RECORD
