Metadata-Version: 2.1
Name: avalanche-lib
Version: 0.6.0
Summary: Avalanche: a Comprehensive Framework for Continual Learning Research
Home-page: https://github.com/ContinualAI/avalanche
Author: ContinualAI
Author-email: contact@continualai.org
Classifier: Programming Language :: Python :: 3
Classifier: License :: OSI Approved :: MIT License
Classifier: Operating System :: OS Independent
Requires-Python: >=3.8
License-File: LICENSE
Requires-Dist: typing-extensions >=4.6.0
Requires-Dist: psutil
Requires-Dist: gputil
Requires-Dist: scikit-learn
Requires-Dist: matplotlib
Requires-Dist: numpy
Requires-Dist: pytorchcv
Requires-Dist: wandb
Requires-Dist: tensorboard >=1.15
Requires-Dist: tqdm
Requires-Dist: torch
Requires-Dist: torchvision
Requires-Dist: torchmetrics
Requires-Dist: gdown
Requires-Dist: qpsolvers[open_source_solvers]
Requires-Dist: dill
Requires-Dist: packaging
Provides-Extra: all
Requires-Dist: gym ; extra == 'all'
Requires-Dist: ctrl-benchmark ; extra == 'all'
Requires-Dist: sphinx ; extra == 'all'
Requires-Dist: sphinx-autoapi ; extra == 'all'
Requires-Dist: sphinx-rtd-theme ; extra == 'all'
Requires-Dist: sphinx-copybutton ; extra == 'all'
Requires-Dist: pycocotools ; extra == 'all'
Requires-Dist: torchaudio ; extra == 'all'
Requires-Dist: lvis ; extra == 'all'
Requires-Dist: higher ; extra == 'all'
Requires-Dist: timm ; extra == 'all'
Provides-Extra: ctrl
Requires-Dist: ctrl-benchmark ; extra == 'ctrl'
Provides-Extra: detection
Requires-Dist: pycocotools ; extra == 'detection'
Requires-Dist: lvis ; extra == 'detection'
Provides-Extra: dev
Requires-Dist: sphinx-copybutton ; extra == 'dev'
Requires-Dist: sphinx-autoapi ; extra == 'dev'
Requires-Dist: sphinx ; extra == 'dev'
Requires-Dist: sphinx-rtd-theme ; extra == 'dev'
Provides-Extra: extra
Requires-Dist: torchaudio ; extra == 'extra'
Requires-Dist: higher ; extra == 'extra'
Provides-Extra: l2p
Requires-Dist: timm ; extra == 'l2p'
Provides-Extra: rl
Requires-Dist: gym ; extra == 'rl'
